trytond/modules/account_be/__init__.py
trytond/modules/account_be/account.py
trytond/modules/account_be/account.xml
trytond/modules/account_be/account_be_fr.xml
trytond/modules/account_be/account_be_nl.xml
trytond/modules/account_be/ogm_vcs.py
trytond/modules/account_be/tax_be_fr.xml
trytond/modules/account_be/tax_be_nl.xml
trytond/modules/account_be/tryton.cfg
trytond/modules/account_be/locale/bg.po
trytond/modules/account_be/locale/ca.po
trytond/modules/account_be/locale/cs.po
trytond/modules/account_be/locale/de.po
trytond/modules/account_be/locale/es.po
trytond/modules/account_be/locale/es_419.po
trytond/modules/account_be/locale/et.po
trytond/modules/account_be/locale/fa.po
trytond/modules/account_be/locale/fi.po
trytond/modules/account_be/locale/fr.po
trytond/modules/account_be/locale/hu.po
trytond/modules/account_be/locale/id.po
trytond/modules/account_be/locale/it.po
trytond/modules/account_be/locale/lo.po
trytond/modules/account_be/locale/lt.po
trytond/modules/account_be/locale/nl.po
trytond/modules/account_be/locale/pl.po
trytond/modules/account_be/locale/pt.po
trytond/modules/account_be/locale/ro.po
trytond/modules/account_be/locale/ru.po
trytond/modules/account_be/locale/sl.po
trytond/modules/account_be/locale/tr.po
trytond/modules/account_be/locale/uk.po
trytond/modules/account_be/locale/zh_CN.po
trytond/modules/account_be/tests/__init__.py
trytond/modules/account_be/tests/test_module.py
trytond/modules/account_be/view/vat_customer_context_form.xml
trytond/modules/account_be/view/vat_customer_list.xml
trytond_account_be-7.8.1.dist-info/licenses/LICENSE
trytond_account_be-7.8.1.dist-info/METADATA
trytond_account_be-7.8.1.dist-info/WHEEL
trytond_account_be-7.8.1.dist-info/entry_points.txt
trytond_account_be-7.8.1.dist-info/top_level.txt
trytond_account_be-7.8.1.dist-info/RECORD
